socks.py
sockshandler.py
PySocks3.9-2.0.dist-info/LICENSE
PySocks3.9-2.0.dist-info/METADATA
PySocks3.9-2.0.dist-info/WHEEL
PySocks3.9-2.0.dist-info/top_level.txt
PySocks3.9-2.0.dist-info/RECORD
