Metadata-Version: 2.1
Name: PySocks3.9
Version: 2.0
Summary: A Python SOCKS client module. See https://github.com/Anorov/PySocks for more information.
Home-page: https://github.com/Anorov/PySocks
Author: Anorov
Author-email: anorov.vorona@gmail.com
License: BSD
Keywords: socks,proxy
Platform: UNKNOWN
Classifier: Programming Language :: Python :: 2
Classifier: Programming Language :: Python :: 2.7
Classifier: Programming Language :: Python :: 3
Classifier: Programming Language :: Python :: 3.4
Classifier: Programming Language :: Python :: 3.5
Classifier: Programming Language :: Python :: 3.6
Requires-Python: >=2.7, !=3.0.*, !=3.1.*, !=3.2.*, !=3.3.*,!=3.9.*
